finessensual/__about__.py
finessensual/__init__.py
finessensual/analyze.py
finessensual/budget.py
finessensual/costs.py
finessensual/expenditures.py
finessensual/helper.py
finessensual/income.py
finessensual/indexers.py
finessensual/openpyxl_helper.py
finessensual/parsers.py
finessensual/persons.py
finessensual/projects.py
finessensual-0.0.24.dist-info/METADATA
finessensual-0.0.24.dist-info/WHEEL
finessensual-0.0.24.dist-info/entry_points.txt
finessensual-0.0.24.dist-info/licenses/LICENSE.rtf
finessensual-0.0.24.dist-info/licenses/LICENSE.txt
finessensual-0.0.24.dist-info/RECORD
