Metadata-Version: 2.4
Name: finessensual
Version: 0.0.24
Summary: a package and script to ease the financial planning of a research group, using Oracle Financials data from UAntwerp
Project-URL: Documentation, https://-/finessensual#readme
Project-URL: Issues, https://-/finessensual/issues
Project-URL: Source, https://-/finessensual
Author-email: Walter Daems <walter.daems@uantwerpen.be>
License-Expression: MIT
License-File: LICENSE.rtf
License-File: LICENSE.txt
Classifier: Operating System :: OS Independent
Classifier: Programming Language :: Python :: 3.12
Requires-Python: >=3.8
Requires-Dist: openpyxl
